bioenergetics/__init__.py
bioenergetics/infection.py
bioenergetics/model.py
bioenergetics/params.py
bioenergetics/prey.py
bioenergetics/util.py
bioenergetics-0.1.0.dist-info/LICENSE
bioenergetics-0.1.0.dist-info/WHEEL
bioenergetics-0.1.0.dist-info/METADATA
bioenergetics-0.1.0.dist-info/RECORD
